{"cameraMode":{"drawMode":0,"name":"Shaded","section":"Shading Mode"},"sceneLighting":true,"audioPlay":false,"sceneViewState":{"m_AlwaysRefresh":false,"showFog":true,"showSkybox":true,"showFlares":true,"showImageEffects":true,"showParticleSystems":true,"showVisualEffectGraphs":true,"m_FxEnabled":true},"in2DMode":false,"pivot":{"x":35.79999923706055,"y":100.0,"z":19.100000381469728},"rotation":{"x":0.2327127754688263,"y":-0.01604599691927433,"z":0.003839066717773676,"w":0.9724061489105225},"size":10.0,"orthographic":false}